{
  "generator-jhipster": {
    "applicationType": "microservice",
    "authenticationType": "oauth2",
    "baseName": "userservice",
    "blueprints": [],
    "buildTool": "maven",
    "cacheProvider": "no",
    "clientFramework": "no",
    "creationTimestamp": 1681281377377,
    "databaseType": "sql",
    "devDatabaseType": "postgresql",
    "dtoSuffix": "DTO",
    "enableGradleEnterprise": false,
    "enableHibernateCache": false,
    "enableSwaggerCodegen": false,
    "enableTranslation": false,
    "entitySuffix": "",
    "jhiPrefix": "jhi",
    "jhipsterVersion": "7.9.3",
    "jwtSecretKey": "ZTBjOGVmZTcwOWM4NzVkZDY3NmQ5Y2QyYTA4YzVhOWI0YTg4ZGZkNTNiNGMwY2ZiNDAxMGVmZDI0ZWM5NGE2MjQwZGNiNTU0NDk5ODExN2Y2YWNiNzVkOWUzYmFmMjRmMzg4OTA5NTYyNGI4MTViM2YwOTJkOGQ2ZDA3YmQ1YjU=",
    "languages": ["en", "fr"],
    "messageBroker": false,
    "microfrontend": false,
    "microfrontends": [],
    "monorepository": true,
    "nativeLanguage": "en",
    "otherModules": [],
    "packageName": "com.app.userservice",
    "pages": [],
    "prodDatabaseType": "postgresql",
    "reactive": false,
    "searchEngine": false,
    "serverPort": "8081",
    "serverSideOptions": [],
    "serviceDiscoveryType": "eureka",
    "skipCheckLengthOfIdentifier": false,
    "skipClient": true,
    "skipCommitHook": true,
    "skipFakeData": false,
    "skipUserManagement": true,
    "testFrameworks": [],
    "websocket": false,
    "withAdminUi": false
  }
}
